<stg><name>control_Pipeline_VITIS_LOOP_736_1_VITIS_LOOP_737_247</name>


<trans_list>

<trans id="96" from="1" to="2">
<condition id="-1">
<or_exp><and_exp></and_exp></or_exp>
</condition>
</trans>

<trans id="85" from="2" to="3">
<condition id="-1">
<or_exp><and_exp></and_exp></or_exp>
</condition>
</trans>

<trans id="86" from="3" to="4">
<condition id="-1">
<or_exp><and_exp></and_exp></or_exp>
</condition>
</trans>

<trans id="87" from="4" to="5">
<condition id="-1">
<or_exp><and_exp></and_exp></or_exp>
</condition>
</trans>

<trans id="88" from="5" to="6">
<condition id="-1">
<or_exp><and_exp></and_exp></or_exp>
</condition>
</trans>

<trans id="89" from="6" to="7">
<condition id="-1">
<or_exp><and_exp></and_exp></or_exp>
</condition>
</trans>

<trans id="90" from="7" to="8">
<condition id="-1">
<or_exp><and_exp></and_exp></or_exp>
</condition>
</trans>

<trans id="91" from="8" to="9">
<condition id="-1">
<or_exp><and_exp></and_exp></or_exp>
</condition>
</trans>

<trans id="92" from="9" to="10">
<condition id="-1">
<or_exp><and_exp></and_exp></or_exp>
</condition>
</trans>

<trans id="93" from="10" to="11">
<condition id="-1">
<or_exp><and_exp></and_exp></or_exp>
</condition>
</trans>
</trans_list>



<state_list>

<state id="1" st_id="2">

<operation id="14" st_id="1" stage="1" lat="1">
<core>NULL</core>
<MemPortIdVec></MemPortIdVec>
<condition id="-1">
<or_exp><and_exp></and_exp></or_exp>
</condition>

<Node id="5" bw="9" op_0_bw="32">
<![CDATA[
newFuncRoot:0 %v302 = alloca i32 1

]]></Node>
<StgValue><ssdm name="v302"/></StgValue>
</operation>

<operation id="15" st_id="1" stage="1" lat="1">
<core>NULL</core>
<MemPortIdVec></MemPortIdVec>
<condition id="-1">
<or_exp><and_exp></and_exp></or_exp>
</condition>

<Node id="6" bw="7" op_0_bw="32">
<![CDATA[
newFuncRoot:1 %v301 = alloca i32 1

]]></Node>
<StgValue><ssdm name="v301"/></StgValue>
</operation>

<operation id="16" st_id="1" stage="1" lat="1">
<core>NULL</core>
<MemPortIdVec></MemPortIdVec>
<condition id="-1">
<or_exp><and_exp></and_exp></or_exp>
</condition>

<Node id="7" bw="15" op_0_bw="32">
<![CDATA[
newFuncRoot:2 %indvar_flatten14789 = alloca i32 1

]]></Node>
<StgValue><ssdm name="indvar_flatten14789"/></StgValue>
</operation>

<operation id="17" st_id="1" stage="1" lat="1">
<core>NULL</core>
<MemPortIdVec></MemPortIdVec>
<condition id="-1">
<or_exp><and_exp></and_exp></or_exp>
</condition>

<Node id="8" bw="64" op_0_bw="64" op_1_bw="64">
<![CDATA[
newFuncRoot:3 %v1013_read = read i64 @_ssdm_op_Read.ap_auto.i64, i64 %v1013

]]></Node>
<StgValue><ssdm name="v1013_read"/></StgValue>
</operation>

<operation id="18" st_id="1" stage="1" lat="1">
<core>NULL</core>
<MemPortIdVec></MemPortIdVec>
<condition id="-1">
<or_exp><and_exp></and_exp></or_exp>
</condition>

<Node id="9" bw="62" op_0_bw="62" op_1_bw="62">
<![CDATA[
newFuncRoot:4 %sext_ln736_read = read i62 @_ssdm_op_Read.ap_auto.i62, i62 %sext_ln736

]]></Node>
<StgValue><ssdm name="sext_ln736_read"/></StgValue>
</operation>

<operation id="19" st_id="1" stage="1" lat="1">
<core>NULL</core>
<MemPortIdVec></MemPortIdVec>
<condition id="-1">
<or_exp><and_exp></and_exp></or_exp>
</condition>

<Node id="10" bw="62" op_0_bw="62" op_1_bw="62">
<![CDATA[
newFuncRoot:5 %sext_ln8973 = read i62 @_ssdm_op_Read.ap_auto.i62, i62 %sext_ln897

]]></Node>
<StgValue><ssdm name="sext_ln8973"/></StgValue>
</operation>

<operation id="20" st_id="1" stage="1" lat="1">
<core>NULL</core>
<MemPortIdVec></MemPortIdVec>
<condition id="-1">
<or_exp><and_exp></and_exp></or_exp>
</condition>

<Node id="11" bw="64" op_0_bw="62">
<![CDATA[
newFuncRoot:6 %sext_ln736_cast = sext i62 %sext_ln736_read

]]></Node>
<StgValue><ssdm name="sext_ln736_cast"/></StgValue>
</operation>

<operation id="21" st_id="1" stage="1" lat="1">
<core>NULL</core>
<MemPortIdVec></MemPortIdVec>
<condition id="-1">
<or_exp><and_exp></and_exp></or_exp>
</condition>

<Node id="12" bw="0" op_0_bw="0" op_1_bw="32" op_2_bw="1" op_3_bw="0">
<![CDATA[
newFuncRoot:7 %specstablecontent_ln0 = specstablecontent void @_ssdm_op_SpecStableContent, i32 %g0, i1 1, void 

]]></Node>
<StgValue><ssdm name="specstablecontent_ln0"/></StgValue>
</operation>

<operation id="22" st_id="1" stage="1" lat="1">
<core>NULL</core>
<MemPortIdVec></MemPortIdVec>
<condition id="-1">
<or_exp><and_exp></and_exp></or_exp>
</condition>

<Node id="13" bw="0" op_0_bw="0" op_1_bw="32" op_2_bw="0" op_3_bw="32" op_4_bw="32" op_5_bw="0" op_6_bw="32" op_7_bw="32" op_8_bw="0" op_9_bw="0" op_10_bw="0" op_11_bw="32" op_12_bw="32" op_13_bw="32" op_14_bw="32" op_15_bw="0" op_16_bw="0" op_17_bw="32" op_18_bw="32" op_19_bw="32" op_20_bw="32">
<![CDATA[
newFuncRoot:8 %specinterface_ln0 = specinterface void @_ssdm_op_SpecInterface, i32 %g0, void @empty_26, i32 0, i32 0, void @empty_35, i32 0, i32 0, void @empty_22, void @empty_25, void @empty_35, i32 16, i32 16, i32 16, i32 16, void @empty_35, void @empty_35, i32 4294967295, i32 0, i32 0, i32 4

]]></Node>
<StgValue><ssdm name="specinterface_ln0"/></StgValue>
</operation>

<operation id="23" st_id="1" stage="1" lat="1">
<core>NULL</core>
<MemPortIdVec></MemPortIdVec>
<condition id="-1">
<or_exp><and_exp></and_exp></or_exp>
</condition>

<Node id="14" bw="0" op_0_bw="15" op_1_bw="15">
<![CDATA[
newFuncRoot:9 %store_ln0 = store i15 0, i15 %indvar_flatten14789

]]></Node>
<StgValue><ssdm name="store_ln0"/></StgValue>
</operation>

<operation id="24" st_id="1" stage="1" lat="1">
<core>NULL</core>
<MemPortIdVec></MemPortIdVec>
<condition id="-1">
<or_exp><and_exp></and_exp></or_exp>
</condition>

<Node id="15" bw="0" op_0_bw="7" op_1_bw="7">
<![CDATA[
newFuncRoot:10 %store_ln736 = store i7 0, i7 %v301

]]></Node>
<StgValue><ssdm name="store_ln736"/></StgValue>
</operation>

<operation id="25" st_id="1" stage="1" lat="1">
<core>NULL</core>
<MemPortIdVec></MemPortIdVec>
<condition id="-1">
<or_exp><and_exp></and_exp></or_exp>
</condition>

<Node id="16" bw="0" op_0_bw="9" op_1_bw="9">
<![CDATA[
newFuncRoot:11 %store_ln737 = store i9 0, i9 %v302

]]></Node>
<StgValue><ssdm name="store_ln737"/></StgValue>
</operation>

<operation id="26" st_id="1" stage="1" lat="1">
<core>NULL</core>
<MemPortIdVec></MemPortIdVec>
<condition id="-1">
<or_exp><and_exp></and_exp></or_exp>
</condition>

<Node id="17" bw="0" op_0_bw="0">
<![CDATA[
newFuncRoot:12 %br_ln0 = br void %for.inc.i1787

]]></Node>
<StgValue><ssdm name="br_ln0"/></StgValue>
</operation>

<operation id="27" st_id="1" stage="1" lat="1">
<core>NULL</core>
<MemPortIdVec></MemPortIdVec>
<condition id="-1">
<or_exp><and_exp></and_exp></or_exp>
</condition>

<Node id="19" bw="15" op_0_bw="15" op_1_bw="0">
<![CDATA[
for.inc.i1787:0 %indvar_flatten14789_load = load i15 %indvar_flatten14789

]]></Node>
<StgValue><ssdm name="indvar_flatten14789_load"/></StgValue>
</operation>

<operation id="28" st_id="1" stage="1" lat="1">
<core>NULL</core>
<MemPortIdVec></MemPortIdVec>
<condition id="-1">
<or_exp><and_exp></and_exp></or_exp>
</condition>

<Node id="20" bw="0" op_0_bw="0" op_1_bw="32">
<![CDATA[
for.inc.i1787:1 %specbitsmap_ln0 = specbitsmap void @_ssdm_op_SpecBitsMap, i32 %g0

]]></Node>
<StgValue><ssdm name="specbitsmap_ln0"/></StgValue>
</operation>

<operation id="29" st_id="1" stage="1" lat="1">
<core>Cmp</core>
<MemPortIdVec></MemPortIdVec>
<condition id="-1">
<or_exp><and_exp></and_exp></or_exp>
</condition>

<Node id="21" bw="1" op_0_bw="15" op_1_bw="15">
<![CDATA[
for.inc.i1787:2 %icmp_ln736 = icmp_eq  i15 %indvar_flatten14789_load, i15 24576

]]></Node>
<StgValue><ssdm name="icmp_ln736"/></StgValue>
</operation>

<operation id="30" st_id="1" stage="1" lat="1">
<core>Adder</core>
<MemPortIdVec></MemPortIdVec>
<condition id="-1">
<or_exp><and_exp></and_exp></or_exp>
</condition>

<Node id="22" bw="15" op_0_bw="15" op_1_bw="15">
<![CDATA[
for.inc.i1787:3 %add_ln736 = add i15 %indvar_flatten14789_load, i15 1

]]></Node>
<StgValue><ssdm name="add_ln736"/></StgValue>
</operation>

<operation id="31" st_id="1" stage="1" lat="1">
<core>NULL</core>
<MemPortIdVec></MemPortIdVec>
<condition id="-1">
<or_exp><and_exp></and_exp></or_exp>
</condition>

<Node id="23" bw="0" op_0_bw="1" op_1_bw="0" op_2_bw="0">
<![CDATA[
for.inc.i1787:4 %br_ln736 = br i1 %icmp_ln736, void %for.inc15.i1790, void %_Z8kernel54PA64_A12_A32_fPA64_A384_f.exit1791.exitStub

]]></Node>
<StgValue><ssdm name="br_ln736"/></StgValue>
</operation>

<operation id="32" st_id="1" stage="1" lat="1">
<core>NULL</core>
<MemPortIdVec></MemPortIdVec>
<condition id="-1">
<or_exp><and_exp><literal name="icmp_ln736" val="0"/>
</and_exp></or_exp>
</condition>

<Node id="25" bw="9" op_0_bw="9" op_1_bw="0">
<![CDATA[
for.inc15.i1790:0 %v302_load = load i9 %v302

]]></Node>
<StgValue><ssdm name="v302_load"/></StgValue>
</operation>

<operation id="33" st_id="1" stage="1" lat="1">
<core>NULL</core>
<MemPortIdVec></MemPortIdVec>
<condition id="-1">
<or_exp><and_exp><literal name="icmp_ln736" val="0"/>
</and_exp></or_exp>
</condition>

<Node id="26" bw="7" op_0_bw="7" op_1_bw="0">
<![CDATA[
for.inc15.i1790:1 %v301_load = load i7 %v301

]]></Node>
<StgValue><ssdm name="v301_load"/></StgValue>
</operation>

<operation id="34" st_id="1" stage="1" lat="1">
<core>Adder</core>
<MemPortIdVec></MemPortIdVec>
<condition id="-1">
<or_exp><and_exp><literal name="icmp_ln736" val="0"/>
</and_exp></or_exp>
</condition>

<Node id="28" bw="7" op_0_bw="7" op_1_bw="7">
<![CDATA[
for.inc15.i1790:3 %add_ln736_1 = add i7 %v301_load, i7 1

]]></Node>
<StgValue><ssdm name="add_ln736_1"/></StgValue>
</operation>

<operation id="35" st_id="1" stage="1" lat="1">
<core>Cmp</core>
<MemPortIdVec></MemPortIdVec>
<condition id="-1">
<or_exp><and_exp><literal name="icmp_ln736" val="0"/>
</and_exp></or_exp>
</condition>

<Node id="31" bw="1" op_0_bw="9" op_1_bw="9">
<![CDATA[
for.inc15.i1790:6 %icmp_ln737 = icmp_eq  i9 %v302_load, i9 384

]]></Node>
<StgValue><ssdm name="icmp_ln737"/></StgValue>
</operation>

<operation id="36" st_id="1" stage="1" lat="1">
<core>Sel</core>
<MemPortIdVec></MemPortIdVec>
<condition id="-1">
<or_exp><and_exp><literal name="icmp_ln736" val="0"/>
</and_exp></or_exp>
</condition>

<Node id="32" bw="9" op_0_bw="1" op_1_bw="9" op_2_bw="9">
<![CDATA[
for.inc15.i1790:7 %select_ln736 = select i1 %icmp_ln737, i9 0, i9 %v302_load

]]></Node>
<StgValue><ssdm name="select_ln736"/></StgValue>
</operation>

<operation id="37" st_id="1" stage="1" lat="1">
<core>Sel</core>
<MemPortIdVec></MemPortIdVec>
<condition id="-1">
<or_exp><and_exp><literal name="icmp_ln736" val="0"/>
</and_exp></or_exp>
</condition>

<Node id="33" bw="7" op_0_bw="1" op_1_bw="7" op_2_bw="7">
<![CDATA[
for.inc15.i1790:8 %select_ln736_1 = select i1 %icmp_ln737, i7 %add_ln736_1, i7 %v301_load

]]></Node>
<StgValue><ssdm name="select_ln736_1"/></StgValue>
</operation>

<operation id="38" st_id="1" stage="1" lat="1">
<core>NULL</core>
<MemPortIdVec></MemPortIdVec>
<condition id="-1">
<or_exp><and_exp><literal name="icmp_ln736" val="0"/>
</and_exp></or_exp>
</condition>

<Node id="34" bw="18" op_0_bw="18" op_1_bw="7" op_2_bw="11">
<![CDATA[
for.inc15.i1790:9 %p_shl = bitconcatenate i18 @_ssdm_op_BitConcatenate.i18.i7.i11, i7 %select_ln736_1, i11 0

]]></Node>
<StgValue><ssdm name="p_shl"/></StgValue>
</operation>

<operation id="39" st_id="1" stage="1" lat="1">
<core>NULL</core>
<MemPortIdVec></MemPortIdVec>
<condition id="-1">
<or_exp><and_exp><literal name="icmp_ln736" val="0"/>
</and_exp></or_exp>
</condition>

<Node id="35" bw="16" op_0_bw="16" op_1_bw="7" op_2_bw="9">
<![CDATA[
for.inc15.i1790:10 %tmp = bitconcatenate i16 @_ssdm_op_BitConcatenate.i16.i7.i9, i7 %select_ln736_1, i9 0

]]></Node>
<StgValue><ssdm name="tmp"/></StgValue>
</operation>

<operation id="40" st_id="1" stage="1" lat="1">
<core>NULL</core>
<MemPortIdVec></MemPortIdVec>
<condition id="-1">
<or_exp><and_exp><literal name="icmp_ln736" val="0"/>
</and_exp></or_exp>
</condition>

<Node id="36" bw="18" op_0_bw="16">
<![CDATA[
for.inc15.i1790:11 %zext_ln741 = zext i16 %tmp

]]></Node>
<StgValue><ssdm name="zext_ln741"/></StgValue>
</operation>

<operation id="41" st_id="1" stage="1" lat="1">
<core>Adder</core>
<MemPortIdVec></MemPortIdVec>
<condition id="-1">
<or_exp><and_exp><literal name="icmp_ln736" val="0"/>
</and_exp></or_exp>
</condition>

<Node id="37" bw="18" op_0_bw="18" op_1_bw="18">
<![CDATA[
for.inc15.i1790:12 %sub_ln741 = sub i18 %p_shl, i18 %zext_ln741

]]></Node>
<StgValue><ssdm name="sub_ln741"/></StgValue>
</operation>

<operation id="42" st_id="1" stage="1" lat="1">
<core>NULL</core>
<MemPortIdVec></MemPortIdVec>
<condition id="-1">
<or_exp><and_exp><literal name="icmp_ln736" val="0"/>
</and_exp></or_exp>
</condition>

<Node id="38" bw="64" op_0_bw="18">
<![CDATA[
for.inc15.i1790:13 %zext_ln737 = zext i18 %sub_ln741

]]></Node>
<StgValue><ssdm name="zext_ln737"/></StgValue>
</operation>

<operation id="43" st_id="1" stage="1" lat="1">
<core>TAddSub</core>
<MemPortIdVec></MemPortIdVec>
<condition id="-1">
<or_exp><and_exp><literal name="icmp_ln736" val="0"/>
</and_exp></or_exp>
</condition>

<Node id="40" bw="64" op_0_bw="64" op_1_bw="64">
<![CDATA[
for.inc15.i1790:15 %add_ln741 = add i64 %zext_ln737, i64 %v1013_read

]]></Node>
<StgValue><ssdm name="add_ln741"/></StgValue>
</operation>

<operation id="44" st_id="1" stage="1" lat="1">
<core>NULL</core>
<MemPortIdVec></MemPortIdVec>
<condition id="-1">
<or_exp><and_exp><literal name="icmp_ln736" val="0"/>
</and_exp></or_exp>
</condition>

<Node id="41" bw="11" op_0_bw="11" op_1_bw="9" op_2_bw="2">
<![CDATA[
for.inc15.i1790:16 %tmp2 = bitconcatenate i11 @_ssdm_op_BitConcatenate.i11.i9.i2, i9 %select_ln736, i2 0

]]></Node>
<StgValue><ssdm name="tmp2"/></StgValue>
</operation>

<operation id="45" st_id="1" stage="1" lat="1">
<core>NULL</core>
<MemPortIdVec></MemPortIdVec>
<condition id="-1">
<or_exp><and_exp><literal name="icmp_ln736" val="0"/>
</and_exp></or_exp>
</condition>

<Node id="42" bw="64" op_0_bw="11">
<![CDATA[
for.inc15.i1790:17 %zext_ln741_1 = zext i11 %tmp2

]]></Node>
<StgValue><ssdm name="zext_ln741_1"/></StgValue>
</operation>

<operation id="46" st_id="1" stage="1" lat="1">
<core>TAddSub</core>
<MemPortIdVec></MemPortIdVec>
<condition id="-1">
<or_exp><and_exp><literal name="icmp_ln736" val="0"/>
</and_exp></or_exp>
</condition>

<Node id="43" bw="64" op_0_bw="64" op_1_bw="64">
<![CDATA[
for.inc15.i1790:18 %add_ln741_1 = add i64 %zext_ln741_1, i64 %add_ln741

]]></Node>
<StgValue><ssdm name="add_ln741_1"/></StgValue>
</operation>

<operation id="47" st_id="1" stage="1" lat="1">
<core>NULL</core>
<MemPortIdVec></MemPortIdVec>
<condition id="-1">
<or_exp><and_exp><literal name="icmp_ln736" val="0"/>
</and_exp></or_exp>
</condition>

<Node id="44" bw="62" op_0_bw="62" op_1_bw="64" op_2_bw="32" op_3_bw="32">
<![CDATA[
for.inc15.i1790:19 %trunc_ln741_7 = partselect i62 @_ssdm_op_PartSelect.i62.i64.i32.i32, i64 %add_ln741_1, i32 2, i32 63

]]></Node>
<StgValue><ssdm name="trunc_ln741_7"/></StgValue>
</operation>

<operation id="48" st_id="1" stage="1" lat="1">
<core>NULL</core>
<MemPortIdVec></MemPortIdVec>
<condition id="-1">
<or_exp><and_exp><literal name="icmp_ln736" val="0"/>
</and_exp></or_exp>
</condition>

<Node id="45" bw="64" op_0_bw="62">
<![CDATA[
for.inc15.i1790:20 %sext_ln741 = sext i62 %trunc_ln741_7

]]></Node>
<StgValue><ssdm name="sext_ln741"/></StgValue>
</operation>

<operation id="49" st_id="1" stage="1" lat="1">
<core>NULL</core>
<MemPortIdVec></MemPortIdVec>
<condition id="-1">
<or_exp><and_exp><literal name="icmp_ln736" val="0"/>
</and_exp></or_exp>
</condition>

<Node id="46" bw="32" op_0_bw="32" op_1_bw="64">
<![CDATA[
for.inc15.i1790:21 %g0_addr_63 = getelementptr i32 %g0, i64 %sext_ln741

]]></Node>
<StgValue><ssdm name="g0_addr_63"/></StgValue>
</operation>

<operation id="50" st_id="1" stage="1" lat="1">
<core>Adder</core>
<MemPortIdVec></MemPortIdVec>
<condition id="-1">
<or_exp><and_exp><literal name="icmp_ln736" val="0"/>
</and_exp></or_exp>
</condition>

<Node id="50" bw="9" op_0_bw="9" op_1_bw="9">
<![CDATA[
for.inc15.i1790:25 %add_ln737 = add i9 %select_ln736, i9 1

]]></Node>
<StgValue><ssdm name="add_ln737"/></StgValue>
</operation>

<operation id="51" st_id="1" stage="1" lat="1">
<core>NULL</core>
<MemPortIdVec></MemPortIdVec>
<condition id="-1">
<or_exp><and_exp><literal name="icmp_ln736" val="0"/>
</and_exp></or_exp>
</condition>

<Node id="51" bw="0" op_0_bw="15" op_1_bw="15" op_2_bw="0" op_3_bw="0">
<![CDATA[
for.inc15.i1790:26 %store_ln736 = store i15 %add_ln736, i15 %indvar_flatten14789

]]></Node>
<StgValue><ssdm name="store_ln736"/></StgValue>
</operation>

<operation id="52" st_id="1" stage="1" lat="1">
<core>NULL</core>
<MemPortIdVec></MemPortIdVec>
<condition id="-1">
<or_exp><and_exp><literal name="icmp_ln736" val="0"/>
</and_exp></or_exp>
</condition>

<Node id="52" bw="0" op_0_bw="7" op_1_bw="7" op_2_bw="0" op_3_bw="0">
<![CDATA[
for.inc15.i1790:27 %store_ln736 = store i7 %select_ln736_1, i7 %v301

]]></Node>
<StgValue><ssdm name="store_ln736"/></StgValue>
</operation>

<operation id="53" st_id="1" stage="1" lat="1">
<core>NULL</core>
<MemPortIdVec></MemPortIdVec>
<condition id="-1">
<or_exp><and_exp><literal name="icmp_ln736" val="0"/>
</and_exp></or_exp>
</condition>

<Node id="53" bw="0" op_0_bw="9" op_1_bw="9" op_2_bw="0" op_3_bw="0">
<![CDATA[
for.inc15.i1790:28 %store_ln737 = store i9 %add_ln737, i9 %v302

]]></Node>
<StgValue><ssdm name="store_ln737"/></StgValue>
</operation>
</state>

<state id="2" st_id="3">

<operation id="54" st_id="2" stage="8" lat="8">
<core>m_axi</core>
<MemPortIdVec></MemPortIdVec>
<condition id="-1">
<or_exp><and_exp></and_exp></or_exp>
</condition>

<Node id="47" bw="1" op_0_bw="1" op_1_bw="32" op_2_bw="64">
<![CDATA[
for.inc15.i1790:22 %v303_3_req = readreq i1 @_ssdm_op_ReadReq.m_axi.i32P1A, i32 %g0_addr_63, i64 1

]]></Node>
<StgValue><ssdm name="v303_3_req"/></StgValue>
</operation>
</state>

<state id="3" st_id="4">

<operation id="55" st_id="3" stage="7" lat="8">
<core>m_axi</core>
<MemPortIdVec></MemPortIdVec>
<condition id="-1">
<or_exp><and_exp></and_exp></or_exp>
</condition>

<Node id="47" bw="1" op_0_bw="1" op_1_bw="32" op_2_bw="64">
<![CDATA[
for.inc15.i1790:22 %v303_3_req = readreq i1 @_ssdm_op_ReadReq.m_axi.i32P1A, i32 %g0_addr_63, i64 1

]]></Node>
<StgValue><ssdm name="v303_3_req"/></StgValue>
</operation>
</state>

<state id="4" st_id="5">

<operation id="56" st_id="4" stage="6" lat="8">
<core>m_axi</core>
<MemPortIdVec></MemPortIdVec>
<condition id="-1">
<or_exp><and_exp></and_exp></or_exp>
</condition>

<Node id="47" bw="1" op_0_bw="1" op_1_bw="32" op_2_bw="64">
<![CDATA[
for.inc15.i1790:22 %v303_3_req = readreq i1 @_ssdm_op_ReadReq.m_axi.i32P1A, i32 %g0_addr_63, i64 1

]]></Node>
<StgValue><ssdm name="v303_3_req"/></StgValue>
</operation>
</state>

<state id="5" st_id="6">

<operation id="57" st_id="5" stage="5" lat="8">
<core>m_axi</core>
<MemPortIdVec></MemPortIdVec>
<condition id="-1">
<or_exp><and_exp></and_exp></or_exp>
</condition>

<Node id="47" bw="1" op_0_bw="1" op_1_bw="32" op_2_bw="64">
<![CDATA[
for.inc15.i1790:22 %v303_3_req = readreq i1 @_ssdm_op_ReadReq.m_axi.i32P1A, i32 %g0_addr_63, i64 1

]]></Node>
<StgValue><ssdm name="v303_3_req"/></StgValue>
</operation>
</state>

<state id="6" st_id="7">

<operation id="58" st_id="6" stage="4" lat="8">
<core>m_axi</core>
<MemPortIdVec></MemPortIdVec>
<condition id="-1">
<or_exp><and_exp></and_exp></or_exp>
</condition>

<Node id="47" bw="1" op_0_bw="1" op_1_bw="32" op_2_bw="64">
<![CDATA[
for.inc15.i1790:22 %v303_3_req = readreq i1 @_ssdm_op_ReadReq.m_axi.i32P1A, i32 %g0_addr_63, i64 1

]]></Node>
<StgValue><ssdm name="v303_3_req"/></StgValue>
</operation>
</state>

<state id="7" st_id="8">

<operation id="59" st_id="7" stage="3" lat="8">
<core>m_axi</core>
<MemPortIdVec></MemPortIdVec>
<condition id="-1">
<or_exp><and_exp></and_exp></or_exp>
</condition>

<Node id="47" bw="1" op_0_bw="1" op_1_bw="32" op_2_bw="64">
<![CDATA[
for.inc15.i1790:22 %v303_3_req = readreq i1 @_ssdm_op_ReadReq.m_axi.i32P1A, i32 %g0_addr_63, i64 1

]]></Node>
<StgValue><ssdm name="v303_3_req"/></StgValue>
</operation>
</state>

<state id="8" st_id="9">

<operation id="60" st_id="8" stage="2" lat="8">
<core>m_axi</core>
<MemPortIdVec></MemPortIdVec>
<condition id="-1">
<or_exp><and_exp></and_exp></or_exp>
</condition>

<Node id="47" bw="1" op_0_bw="1" op_1_bw="32" op_2_bw="64">
<![CDATA[
for.inc15.i1790:22 %v303_3_req = readreq i1 @_ssdm_op_ReadReq.m_axi.i32P1A, i32 %g0_addr_63, i64 1

]]></Node>
<StgValue><ssdm name="v303_3_req"/></StgValue>
</operation>
</state>

<state id="9" st_id="10">

<operation id="61" st_id="9" stage="1" lat="8">
<core>m_axi</core>
<MemPortIdVec></MemPortIdVec>
<condition id="-1">
<or_exp><and_exp></and_exp></or_exp>
</condition>

<Node id="47" bw="1" op_0_bw="1" op_1_bw="32" op_2_bw="64">
<![CDATA[
for.inc15.i1790:22 %v303_3_req = readreq i1 @_ssdm_op_ReadReq.m_axi.i32P1A, i32 %g0_addr_63, i64 1

]]></Node>
<StgValue><ssdm name="v303_3_req"/></StgValue>
</operation>
</state>

<state id="10" st_id="11">

<operation id="62" st_id="10" stage="1" lat="1">
<core>m_axi</core>
<MemPortIdVec></MemPortIdVec>
<condition id="-1">
<or_exp><and_exp></and_exp></or_exp>
</condition>

<Node id="48" bw="32" op_0_bw="32" op_1_bw="32" op_2_bw="0">
<![CDATA[
for.inc15.i1790:23 %v303 = read i32 @_ssdm_op_Read.m_axi.i32P1A, i32 %g0_addr_63

]]></Node>
<StgValue><ssdm name="v303"/></StgValue>
</operation>

<operation id="69" st_id="10" stage="1" lat="1">
<core>NULL</core>
<MemPortIdVec></MemPortIdVec>
<condition id="-1">
<or_exp><and_exp><literal name="icmp_ln736" val="1"/>
</and_exp></or_exp>
</condition>

<Node id="56" bw="0">
<![CDATA[
_Z8kernel54PA64_A12_A32_fPA64_A384_f.exit1791.exitStub:0 %ret_ln0 = ret

]]></Node>
<StgValue><ssdm name="ret_ln0"/></StgValue>
</operation>
</state>

<state id="11" st_id="12">

<operation id="63" st_id="11" stage="1" lat="1">
<core>NULL</core>
<MemPortIdVec></MemPortIdVec>
<condition id="-1">
<or_exp><and_exp></and_exp></or_exp>
</condition>

<Node id="27" bw="32" op_0_bw="32" op_1_bw="64">
<![CDATA[
for.inc15.i1790:2 %g0_addr = getelementptr i32 %g0, i64 %sext_ln736_cast

]]></Node>
<StgValue><ssdm name="g0_addr"/></StgValue>
</operation>

<operation id="64" st_id="11" stage="1" lat="1">
<core>NULL</core>
<MemPortIdVec></MemPortIdVec>
<condition id="-1">
<or_exp><and_exp></and_exp></or_exp>
</condition>

<Node id="29" bw="0" op_0_bw="0" op_1_bw="0">
<![CDATA[
for.inc15.i1790:4 %specloopname_ln0 = specloopname void @_ssdm_op_SpecLoopName, void @VITIS_LOOP_736_1_VITIS_LOOP_737_2_str

]]></Node>
<StgValue><ssdm name="specloopname_ln0"/></StgValue>
</operation>

<operation id="65" st_id="11" stage="1" lat="1">
<core>NULL</core>
<MemPortIdVec></MemPortIdVec>
<condition id="-1">
<or_exp><and_exp></and_exp></or_exp>
</condition>

<Node id="30" bw="0" op_0_bw="0" op_1_bw="64" op_2_bw="64" op_3_bw="64">
<![CDATA[
for.inc15.i1790:5 %speclooptripcount_ln0 = speclooptripcount void @_ssdm_op_SpecLoopTripCount, i64 24576, i64 24576, i64 24576

]]></Node>
<StgValue><ssdm name="speclooptripcount_ln0"/></StgValue>
</operation>

<operation id="66" st_id="11" stage="1" lat="1">
<core>NULL</core>
<MemPortIdVec></MemPortIdVec>
<condition id="-1">
<or_exp><and_exp></and_exp></or_exp>
</condition>

<Node id="39" bw="0" op_0_bw="0" op_1_bw="32" op_2_bw="32" op_3_bw="32" op_4_bw="32" op_5_bw="32" op_6_bw="0">
<![CDATA[
for.inc15.i1790:14 %specpipeline_ln738 = specpipeline void @_ssdm_op_SpecPipeline, i32 1, i32 0, i32 0, i32 0, i32 4294967295, void @empty_35

]]></Node>
<StgValue><ssdm name="specpipeline_ln738"/></StgValue>
</operation>

<operation id="67" st_id="11" stage="1" lat="1">
<core>m_axi</core>
<MemPortIdVec></MemPortIdVec>
<condition id="-1">
<or_exp><and_exp></and_exp></or_exp>
</condition>

<Node id="49" bw="0" op_0_bw="0" op_1_bw="32" op_2_bw="32" op_3_bw="4" op_4_bw="0">
<![CDATA[
for.inc15.i1790:24 %write_ln742 = write void @_ssdm_op_Write.m_axi.p1i32.i32, i32 %g0_addr, i32 %v303, i4 15

]]></Node>
<StgValue><ssdm name="write_ln742"/></StgValue>
</operation>

<operation id="68" st_id="11" stage="1" lat="1">
<core>NULL</core>
<MemPortIdVec></MemPortIdVec>
<condition id="-1">
<or_exp><and_exp></and_exp></or_exp>
</condition>

<Node id="54" bw="0" op_0_bw="0">
<![CDATA[
for.inc15.i1790:29 %br_ln737 = br void %for.inc.i1787

]]></Node>
<StgValue><ssdm name="br_ln737"/></StgValue>
</operation>
</state>
</state_list>


<ports>
</ports>


<dataflows>
</dataflows>


</stg>
